Metadata-Version: 2.4
Name: t_office_365
Version: 0.1.25
Summary: An open-source Python package, t_office_365 providing easy-to-use classes and methods for     interacting with Microsoft Office 365 services, including SharePoint, OneDrive, Outlook, and Excel, with features     such as file management, email handling, and spreadsheet operations.
Home-page: https://www.thoughtful.ai/
Author: Thoughtful
Author-email: support@thoughtful.ai
Keywords: t_office_365
Classifier: Intended Audience :: Developers
Classifier: Natural Language :: English
Classifier: Programming Language :: Python :: 3
Classifier: Programming Language :: Python :: 3.9
Requires-Python: >=3.9
Requires-Dist: O365>=2.0.21
Requires-Dist: requests>=2.31.0
Requires-Dist: retry>=0.9.2
Requires-Dist: tzlocal>=4.2
Requires-Dist: openpyxl>=3.1.2
Dynamic: author
Dynamic: author-email
Dynamic: classifier
Dynamic: description
Dynamic: home-page
Dynamic: keywords
Dynamic: requires-dist
Dynamic: requires-python
Dynamic: summary
